solv/__init__.py
solv/_solv.so
solv/solv.py
solv.libs/liblzma-51a76f52.so.5.2.4
solv.libs/libxml2-54d19b2f.so.2.9.7
solv-0.7.32.dist-info/METADATA
solv-0.7.32.dist-info/WHEEL
solv-0.7.32.dist-info/top_level.txt
solv-0.7.32.dist-info/RECORD
solv-0.7.32.dist-info/licenses/LICENSE.BSD
